{"data": {"type": "match", "id": "e329e248-d2e1-4575-8e01-7622ee0b0a60", "attributes": {"titleId": "bluehole-pubg", "shardId": "steam", "tags": null, "matchType": "official", "createdAt": "2026-01-05T14:34:16Z", "duration": 1554, "mapName": "Tiger_Main", "isCustomMatch": false, "seasonState": "progress", "stats": null, "gameMode": "squad"}, "relationships": {"rosters": {"data": [{"type": "roster", "id": "e45d484d-3568-4611-8fcf-0e443023f232"}, {"type": "roster", "id": "e7d63718-076a-423f-b34d-4256eec353a5"}, {"type": "roster", "id": "f82defa0-8783-4ac4-9f3d-7b4ba594aca8"}, {"type": "roster", "id": "40eb9588-c172-49ce-ac86-f76f11b636a9"}, {"type": "roster", "id": "90c55ca3-de28-4b40-b3e9-bc4020131b29"}, {"type": "roster", "id": "0ec3ade7-6970-40b9-9cc5-c21d8be538b3"}, {"type": "roster", "id": "6a9b0903-f946-4716-8b4d-fb38778e1872"}, {"type": "roster", "id": "ea95686d-81d3-484a-b3c4-8b4e4facc242"}, {"type": "roster", "id": "af08ca1d-0a19-4841-9772-9028a1726777"}, {"type": "roster", "id": "ef92b99e-57bc-4a20-bd67-351bb1bbe802"}, {"type": "roster", "id": "6e309304-d922-4c9b-ae3d-f2335352a2c3"}, {"type": "roster", "id": "45edb292-0555-44bb-b093-d8dc6051f0d4"}, {"type": "roster", "id": "7db93a5b-d120-43a4-8428-49f15d2b2fd6"}, {"type": "roster", "id": "df9c592a-a8bf-4470-a9a9-bb11ded1e147"}, {"type": "roster", "id": "2402b2a1-83d6-45dc-91fc-f1c7aa4118e2"}, {"type": "roster", "id": "6c530cc5-1d65-450d-99c4-00ca39765bcd"}, {"type": "roster", "id": "b5d05d90-bab1-46e0-8934-a3e0a3c0b654"}, {"type": "roster", "id": "4178bff3-cc7b-4725-a10e-7638784d0910"}, {"type": "roster", "id": "dc4f6f44-8885-4b05-85e1-52f7eb565488"}, {"type": "roster", "id": "41150ef3-9d04-4eea-9ad2-b9f539dd511b"}, {"type": "roster", "id": "81011e2c-1206-49f7-8e1a-9f1b976a7269"}, {"type": "roster", "id": "af05d2d3-1c2d-48ce-b8fc-6eb5f0ddaaf8"}, {"type": "roster", "id": "c2800251-fe65-4295-acfc-c0520e0d63ac"}, {"type": "roster", "id": "a85e3f55-9cc2-4f15-9a75-afd912f5d77b"}, {"type": "roster", "id": "f83a0f78-96e7-418a-8046-2aeadafbc5bd"}, {"type": "roster", "id": "13f2450f-62ff-4f90-b685-224e7d495ccd"}, {"type": "roster", "id": "843c3799-078c-462b-838e-7c69ae95b8fb"}, {"type": "roster", "id": "9fbb5b20-bd1c-47e9-95d6-4097ba6b0d0b"}, {"type": "roster", "id": "0757d498-0f0d-4bf5-97f4-9f9196deef2b"}]}, "assets": {"data": [{"type": "asset", "id": "7dfb5b4e-ea47-11f0-9046-e6c087f7d05a"}]}}, "links": {"self": "https://api.pubg.com/shards/steam/matches/e329e248-d2e1-4575-8e01-7622ee0b0a60", "schema": ""}}, "included": [{"type": "participant", "id": "860bcfe3-9b43-421e-b35b-a18013567741", "attributes": {"stats": {"DBNOs": 0, "assists": 0, "boosts": 6, "damageDealt": 0, "deathType": "byplayer", "headshotKills": 0, "heals": 1, "killPlace": 52, "killStreaks": 0, "kills": 0, "longestKill": 0, "name": "Summer_a_a_ovo", "playerId": "account.06096ffc77cb4e50929c7e2c8c614f37", "revives": 0, "rideDistance": 4218.0913, "roadKills": 0, "swimDistance": 0, "teamKills": 0, "timeSurvived": 778, "vehicleDestroys": 0, "walkDistance": 1385.1195, "weaponsAcquired": 9, "winPlace": 5}, "actor": "", "shardId": "steam"}}, {"type": "participant", "id": "cd66711f-b9ae-4f58-8525-3d1429e4f139", "attributes": {"stats": {"DBNOs": 0, "assists": 0, "boosts": 2, "damageDealt": 0, "deathType": "byplayer", "headshotKills": 0, "heals": 4, "killPlace": 81, "killStreaks": 0, "kills": 0, "longestKill": 0, "name": "LiangHeMingMing_", "playerId": "account.c2ec3fd0cbed4a3f9159872d12a8fa62", "revives": 0, "rideDistance": 0, "roadKills": 0, "swimDistance": 0, "teamKills": 0, "timeSurvived": 234, "vehicleDestroys": 0, "walkDistance": 419.60995, "weaponsAcquired": 5, "winPlace": 21}, "actor": "", "shardId": "steam"}}, {"type": "participant", "id": "e33133dd-22c0-495d-8cf2-9621404d36e7", "attributes": {"stats": {"DBNOs": 4, "assists": 0, "boosts": 5, "damageDealt": 527.73004, "deathType": "byplayer", "headshotKills": 0, "heals": 1, "killPlace": 3, "killStreaks": 1, "kills": 5, "longestKill": 55.174614, "name": "Baby_Gan_me", "playerId": "account.04562326297d4a37b0ed4ec9ef995128", "revives": 1, "rideDistance": 2313.249, "roadKills": 0, "swimDistance": 0, "teamKills": 0, "timeSurvived": 778, "vehicleDestroys": 0, "walkDistance": 1448.2615, "weaponsAcquired": 9, "winPlace": 11}, "actor": "", "shardId": "steam"}}, {"type": "participant", "id": "9968ebf9-2704-4862-8487-fd1481ae86ba", "attributes": {"stats": {"DBNOs": 1, "assists": 0, "boosts": 7, "damageDealt": 132.74011, "deathType": "byplayer", "headshotKills": 0, "heals": 1, "killPlace": 38, "killStreaks": 1, "kills": 1, "longestKill": 19.642227, "name": "China-Zxw-1204", "playerId": "account.1d03e44c88a74e698ad0977c02b074fa", "revives": 0, "rideDistance": 5364.012, "roadKills": 0, "swimDistance": 0, "teamKills": 0, "timeSurvived": 901, "vehicleDestroys": 0, "walkDistance": 1521.6636, "weaponsAcquired": 11, "winPlace": 10}, "actor": "", "shardId": "steam"}}, {"type": "participant", "id": "d6ca3576-689e-46c5-98a1-b52ddc3f7acc", "attributes": {"stats": {"DBNOs": 0, "assists": 0, "boosts": 0, "damageDealt": 49.178993, "deathType": "byplayer", "headshotKills": 0, "heals": 1, "killPlace": 82, "killStreaks": 0, "kills": 0, "longestKill": 0, "name": "ZhangDeFu917", "playerId": "account.e15a8e377dd64a2c8a8d4133ce5057dc", "revives": 0, "rideDistance": 0, "roadKills": 0, "swimDistance": 0, "teamKills": 0, "timeSurvived": 203, "vehicleDestroys": 0, "walkDistance": 193.65231, "weaponsAcquired": 2, "winPlace": 22}, "actor": "", "shardId": "steam"}}, {"type": "roster", "id": "e7d63718-076a-423f-b34d-4256eec353a5", "attributes": {"stats": {"rank": 21, "teamId": 7}, "won": "false", "shardId": "steam"}, "relationships": {"team": {"data": null}, "participants": {"data": [{"type": "participant", "id": "aba6b2a8-0f18-48e9-9818-f01d3348e42e"}, {"type": "participant", "id": "0711d883-3093-4c41-bbd8-f7521ca78844"}, {"type": "participant", "id": "f65dfa3b-2ceb-41fb-ae7e-684952fc5451"}, {"type": "participant", "id": "cd66711f-b9ae-4f58-8525-3d1429e4f139"}]}}}, {"type": "participant", "id": "f8a1bc82-b0bc-445a-8407-ed23009f9773", "attributes": {"stats": {"DBNOs": 1, "assists": 0, "boosts": 3, "damageDealt": 122.146, "deathType": "byplayer", "headshotKills": 0, "heals": 2, "killPlace": 20, "killStreaks": 1, "kills": 2, "longestKill": 11.547289, "name": "xiaoxian1114", "playerId": "account.16c8c582fdb743808198abaab352f0dc", "revives": 0, "rideDistance": 3906.1492, "roadKills": 0, "swimDistance": 0, "teamKills": 0, "timeSurvived": 794, "vehicleDestroys": 0, "walkDistance": 1459.9697, "weaponsAcquired": 8, "winPlace": 7}, "actor": "", "shardId": "steam"}}, {"type": "participant", "id": "90b05e12-3d6a-4c59-be33-5caecae2cb17", "attributes": {"shardId": "steam", "stats": {"DBNOs": 1, "assists": 0, "boosts": 0, "damageDealt": 100, "deathType": "byplayer", "headshotKills": 0, "heals": 0, "killPlace": 46, "killStreaks": 1, "kills": 1, "longestKill": 0.75444436, "name": "YuezHc", "playerId": "account.6e0b90d0d9a44a5f870f444b3fcab716", "revives": 0, "rideDistance": 0, "roadKills": 0, "swimDistance": 0, "teamKills": 0, "timeSurvived": 166, "vehicleDestroys": 0, "walkDistance": 208.9847, "weaponsAcquired": 1, "winPlace": 25}, "actor": ""}}, {"type": "participant", "id": "b0b1c2a4-163c-479a-b438-47588996fb95", "attributes": {"shardId": "steam", "stats": {"DBNOs": 0, "assists": 0, "boosts": 0, "damageDealt": 0, "deathType": "byplayer", "headshotKills": 0, "heals": 0, "killPlace": 83, "killStreaks": 0, "kills": 0, "longestKill": 0, "name": "IFINTOY", "playerId": "account.a0e54be040d54bf6b4adaa5cbe3e61b0", "revives": 0, "rideDistance": 0, "roadKills": 0, "swimDistance": 0, "teamKills": 0, "timeSurvived": 120, "vehicleDestroys": 0, "walkDistance": 33.938873, "weaponsAcquired": 1, "winPlace": 22}, "actor": ""}}, {"type": "roster", "id": "0757d498-0f0d-4bf5-97f4-9f9196deef2b", "attributes": {"shardId": "steam", "stats": {"rank": 26, "teamId": 11}, "won": "false"}, "relationships": {"team": {"data": null}, "participants": {"data": [{"type": "participant", "id": "a81b99cd-2e68-474c-b3a9-ab770730ff1c"}, {"type": "participant", "id": "07f2ba32-73c6-494a-811a-9ab6777aeefd"}, {"type": "participant", "id": "de7df463-aa57-478e-a8bf-6e81c91c2931"}, {"type": "participant", "id": "9f0c27a0-595f-46b2-97a0-57c280cb09ed"}]}}}, {"type": "participant", "id": "e5c92531-bf7d-49e3-af89-bc744e054ed5", "attributes": {"actor": "", "shardId": "steam", "stats": {"DBNOs": 0, "assists": 1, "boosts": 1, "damageDealt": 25.674566, "deathType": "byplayer", "headshotKills": 0, "heals": 0, "killPlace": 69, "killStreaks": 0, "kills": 0, "longestKill": 0, "name": "1jqcas23", "playerId": "account.78b590b4f75d4f2684b87143c5751733", "revives": 1, "rideDistance": 0, "roadKills": 0, "swimDistance": 0, "teamKills": 0, "timeSurvived": 308, "vehicleDestroys": 0, "walkDistance": 685.21954, "weaponsAcquired": 7, "winPlace": 16}}}, {"type": "participant", "id": "6a5d79d3-c0fa-4044-bea1-20fca67672da", "attributes": {"actor": "", "shardId": "steam", "stats": {"DBNOs": 0, "assists": 0, "boosts": 0, "damageDealt": 65.58713, "deathType": "byplayer", "headshotKills": 0, "heals": 0, "killPlace": 60, "killStreaks": 0, "kills": 0, "longestKill": 0, "name": "Kingboy818", "playerId": "account.ddb9544a17c84e70a991ed7e8be41c0b", "revives": 0, "rideDistance": 1.947541, "roadKills": 0, "swimDistance": 0, "teamKills": 0, "timeSurvived": 417, "vehicleDestroys": 0, "walkDistance": 611.9117, "weaponsAcquired": 7, "winPlace": 12}}}, {"type": "participant", "id": "9a102e56-8208-44f4-952c-6b28fbeec41c", "attributes": {"stats": {"DBNOs": 2, "assists": 0, "boosts": 0, "damageDealt": 250.77782, "deathType": "byplayer", "headshotKills": 0, "heals": 0, "killPlace": 25, "killStreaks": 1, "kills": 2, "longestKill": 6.243377, "name": "wy1531_OH", "playerId": "account.ce65115d8f4641a5aafa2ea82352d5b5", "revives": 0, "rideDistance": 0, "roadKills": 0, "swimDistance": 0, "teamKills": 0, "timeSurvived": 254, "vehicleDestroys": 0, "walkDistance": 298.97977, "weaponsAcquired": 3, "winPlace": 17}, "actor": "", "shardId": "steam"}}, {"type": "participant", "id": "880eefe7-2c97-40be-88a6-e428d386d0c6", "attributes": {"shardId": "steam", "stats": {"DBNOs": 0, "assists": 2, "boosts": 2, "damageDealt": 151.00867, "deathType": "byplayer", "headshotKills": 0, "heals": 0, "killPlace": 63, "killStreaks": 0, "kills": 0, "longestKill": 0, "name": "Eagle_Xiuxiu", "playerId": "account.14dc85257d7f41dc80eae19c637e78c3", "revives": 0, "rideDistance": 0, "roadKills": 0, "swimDistance": 0, "teamKills": 0, "timeSurvived": 491, "vehicleDestroys": 0, "walkDistance": 1646.6333, "weaponsAcquired": 7, "winPlace": 13}, "actor": ""}}, {"type": "participant", "id": "a965fad8-93b2-4b03-87f7-13a9efeee090", "attributes": {"stats": {"DBNOs": 1, "assists": 0, "boosts": 2, "damageDealt": 170.86067, "deathType": "alive", "headshotKills": 0, "heals": 1, "killPlace": 28, "killStreaks": 1, "kills": 1, "longestKill": 147.95674, "name": "zzzzlp957", "playerId": "account.f2c5899044a442b6a0070e8726d2e9c7", "revives": 0, "rideDistance": 7727.6016, "roadKills": 0, "swimDistance": 0, "teamKills": 0, "timeSurvived": 1554, "vehicleDestroys": 0, "walkDistance": 2370.6592, "weaponsAcquired": 7, "winPlace": 1}, "actor": "", "shardId": "steam"}}, {"type": "participant", "id": "a4bd780f-7405-463e-8f69-ca28a1f61554", "attributes": {"stats": {"DBNOs": 1, "assists": 0, "boosts": 2, "damageDealt": 141.39412, "deathType": "byplayer", "headshotKills": 0, "heals": 3, "killPlace": 35, "killStreaks": 1, "kills": 1, "longestKill": 9.020838, "name": "Xonnnl", "playerId": "account.ff9f68d93bd548bea558e78f052e341b", "revives": 0, "rideDistance": 1234.0022, "roadKills": 0, "swimDistance": 0, "teamKills": 0, "timeSurvived": 742, "vehicleDestroys": 1, "walkDistance": 1836.3036, "weaponsAcquired": 8, "winPlace": 8}, "actor": "", "shardId": "steam"}}, {"type": "participant", "id": "5b703b4b-80f5-4bfb-aa18-86dff9efdd20", "attributes": {"stats": {"DBNOs": 0, "assists": 1, "boosts": 3, "damageDealt": 47.52, "deathType": "byplayer", "headshotKills": 0, "heals": 1, "killPlace": 54, "killStreaks": 0, "kills": 0, "longestKill": 0, "name": "Holoozz", "playerId": "account.482ace0788884481a59d7a99aebd9963", "revives": 2, "rideDistance": 6600.335, "roadKills": 0, "swimDistance": 0, "teamKills": 0, "timeSurvived": 1003, "vehicleDestroys": 0, "walkDistance": 1578.6519, "weaponsAcquired": 10, "winPlace": 8}, "actor": "", "shardId": "steam"}}, {"type": "participant", "id": "ca08f74f-a1c1-4cb8-a7a5-c94ef8e2a079", "attributes": {"stats": {"DBNOs": 2, "assists": 0, "boosts": 3, "damageDealt": 248.4043, "deathType": "byplayer", "headshotKills": 0, "heals": 0, "killPlace": 14, "killStreaks": 1, "kills": 3, "longestKill": 52.20845, "name": "Gege-wo-36D-_-", "playerId": "account.de077c0cd59a465d8e8d6da0aebd1bef", "revives": 0, "rideDistance": 0, "roadKills": 0, "swimDistance": 0.62571275, "teamKills": 0, "timeSurvived": 548, "vehicleDestroys": 0, "walkDistance": 1627.0094, "weaponsAcquired": 5, "winPlace": 13}, "actor": "", "shardId": "steam"}}, {"type": "participant", "id": "4374f78a-0462-43e8-9b0f-a7c0682a45bb", "attributes": {"stats": {"DBNOs": 0, "assists": 0, "boosts": 0, "damageDealt": 0, "deathType": "byplayer", "headshotKills": 0, "heals": 0, "killPlace": 90, "killStreaks": 0, "kills": 0, "longestKill": 0, "name": "1018-_-_-", "playerId": "account.c12801b8ab33458cbb27b120ca2143ad", "revives": 0, "rideDistance": 0, "roadKills": 0, "swimDistance": 0, "teamKills": 0, "timeSurvived": 66, "vehicleDestroys": 0, "walkDistance": 32.3782, "weaponsAcquired": 1, "winPlace": 25}, "actor": "", "shardId": "steam"}}, {"type": "participant", "id": "07f2ba32-73c6-494a-811a-9ab6777aeefd", "attributes": {"stats": {"DBNOs": 1, "assists": 0, "boosts": 0, "damageDealt": 100, "deathType": "byplayer", "headshotKills": 0, "heals": 0, "killPlace": 93, "killStreaks": 0, "kills": 0, "longestKill": 0, "name": "Kun9zo_", "playerId": "account.4de927e00497476e93850442e7a792af", "revives": 0, "rideDistance": 0, "roadKills": 0, "swimDistance": 0, "teamKills": 0, "timeSurvived": 98, "vehicleDestroys": 0, "walkDistance": 47.391956, "weaponsAcquired": 1, "winPlace": 26}, "actor": "", "shardId": "steam"}}, {"type": "roster", "id": "81011e2c-1206-49f7-8e1a-9f1b976a7269", "attributes": {"stats": {"rank": 10, "teamId": 10}, "won": "false", "shardId": "steam"}, "relationships": {"team": {"data": null}, "participants": {"data": [{"type": "participant", "id": "fb0ae12c-bb0e-45f3-88fe-cb22113919ac"}, {"type": "participant", "id": "9968ebf9-2704-4862-8487-fd1481ae86ba"}, {"type": "participant", "id": "c11fe62e-11f2-4456-8a55-22b235f99549"}, {"type": "participant", "id": "914f555f-48d6-48cc-a037-bebaa3403032"}]}}}, {"type": "roster", "id": "a85e3f55-9cc2-4f15-9a75-afd912f5d77b", "attributes": {"won": "false", "shardId": "steam", "stats": {"rank": 13, "teamId": 1}}, "relationships": {"team": {"data": null}, "participants": {"data": [{"type": "participant", "id": "880eefe7-2c97-40be-88a6-e428d386d0c6"}, {"type": "participant", "id": "ca08f74f-a1c1-4cb8-a7a5-c94ef8e2a079"}, {"type": "participant", "id": "faf41400-103c-4c3f-9073-b6e19ad400d8"}]}}}, {"type": "participant", "id": "32089926-0ce4-44da-8283-34e3140e5013", "attributes": {"stats": {"DBNOs": 0, "assists": 0, "boosts": 0, "damageDealt": 0, "deathType": "byplayer", "headshotKills": 0, "heals": 0, "killPlace": 76, "killStreaks": 0, "kills": 0, "longestKill": 0, "name": "chang_man87", "playerId": "account.e87c3242e1564be3a4bccef3b1b5254e", "revives": 0, "rideDistance": 0, "roadKills": 0, "swimDistance": 0, "teamKills": 0, "timeSurvived": 128, "vehicleDestroys": 0, "walkDistance": 45.09022, "weaponsAcquired": 3, "winPlace": 20}, "actor": "", "shardId": "steam"}}, {"type": "participant", "id": "e0557373-e003-483c-8a3e-6539c8f1e7eb", "attributes": {"stats": {"DBNOs": 0, "assists": 1, "boosts": 6, "damageDealt": 93.6, "deathType": "byplayer", "headshotKills": 0, "heals": 0, "killPlace": 55, "killStreaks": 0, "kills": 0, "longestKill": 0, "name": "HanBarrrrrrrr", "playerId": "account.52007c2ddd024f5080b516145bc96180", "revives": 0, "rideDistance": 7926.461, "roadKills": 0, "swimDistance": 0, "teamKills": 0, "timeSurvived": 899, "vehicleDestroys": 0, "walkDistance": 1321.2131, "weaponsAcquired": 11, "winPlace": 9}, "actor": "", "shardId": "steam"}}, {"type": "participant", "id": "e8cb7223-d942-48c1-816b-4884af88ae2d", "attributes": {"actor": "", "shardId": "steam", "stats": {"DBNOs": 1, "assists": 0, "boosts": 10, "damageDealt": 52.016167, "deathType": "byplayer", "headshotKills": 1, "heals": 0, "killPlace": 16, "killStreaks": 2, "kills": 2, "longestKill": 42.3969, "name": "wjngod123", "playerId": "account.20b057903bb14dfd9d313c238bcc0e75", "revives": 0, "rideDistance": 5584.865, "roadKills": 0, "swimDistance": 0, "teamKills": 0, "timeSurvived": 1482, "vehicleDestroys": 0, "walkDistance": 3148.145, "weaponsAcquired": 15, "winPlace": 3}}}, {"type": "participant", "id": "de7df463-aa57-478e-a8bf-6e81c91c2931", "attributes": {"stats": {"DBNOs": 0, "assists": 0, "boosts": 1, "damageDealt": 76.8, "deathType": "byplayer", "headshotKills": 0, "heals": 0, "killPlace": 92, "killStreaks": 0, "kills": 0, "longestKill": 0, "name": "FllllWD", "playerId": "account.fc933c3b98b54bc09121c30e5589744b", "revives": 0, "rideDistance": 0, "roadKills": 0, "swimDistance": 0, "teamKills": 0, "timeSurvived": 149, "vehicleDestroys": 0, "walkDistance": 262.68903, "weaponsAcquired": 5, "winPlace": 26}, "actor": "", "shardId": "steam"}}, {"type": "participant", "id": "4b172636-3398-41bb-b334-9959288c9fb2", "attributes": {"stats": {"DBNOs": 3, "assists": 3, "boosts": 9, "damageDealt": 524.65967, "deathType": "alive", "headshotKills": 1, "heals": 1, "killPlace": 5, "killStreaks": 1, "kills": 4, "longestKill": 231.50389, "name": "myoo_-", "playerId": "account.f5a129b81d7f4db19d1288abbd2a0202", "revives": 0, "rideDistance": 6972.681, "roadKills": 0, "swimDistance": 0, "teamKills": 0, "timeSurvived": 1554, "vehicleDestroys": 0, "walkDistance": 3155.4138, "weaponsAcquired": 14, "winPlace": 1}, "actor": "", "shardId": "steam"}}, {"type": "participant", "id": "e13a94e1-5394-49f9-8429-b563f88d901e", "attributes": {"stats": {"DBNOs": 2, "assists": 1, "boosts": 4, "damageDealt": 466.3117, "deathType": "byplayer", "headshotKills": 1, "heals": 1, "killPlace": 13, "killStreaks": 2, "kills": 3, "longestKill": 13.215267, "name": "Alph4s", "playerId": "account.6351afbdb69641b68d2e37b90a59a39e", "revives": 0, "rideDistance": 6977.5874, "roadKills": 0, "swimDistance": 0, "teamKills": 0, "timeSurvived": 764, "vehicleDestroys": 0, "walkDistance": 1975.572, "weaponsAcquired": 9, "winPlace": 9}, "actor": "", "shardId": "steam"}}, {"type": "participant", "id": "e6c1c11d-b0a5-4363-9dd4-40cbc8445f47", "attributes": {"stats": {"DBNOs": 0, "assists": 1, "boosts": 8, "damageDealt": 102.37797, "deathType": "byplayer", "headshotKills": 1, "heals": 13, "killPlace": 31, "killStreaks": 1, "kills": 1, "longestKill": 36.700592, "name": "BsSm99H2Z", "playerId": "account.ba9741306cf04612b0096b1b9a619192", "revives": 1, "rideDistance": 7716.509, "roadKills": 0, "swimDistance": 0, "teamKills": 0, "timeSurvived": 1182, "vehicleDestroys": 0, "walkDistance": 1823.9377, "weaponsAcquired": 17, "winPlace": 4}, "actor": "", "shardId": "steam"}}, {"type": "participant", "id": "fc04b721-4960-4e50-8327-8dff8be1ae15", "attributes": {"shardId": "steam", "stats": {"DBNOs": 0, "assists": 0, "boosts": 0, "damageDealt": 18.9, "deathType": "byplayer", "headshotKills": 0, "heals": 0, "killPlace": 85, "killStreaks": 0, "kills": 0, "longestKill": 0, "name": "oiion-", "playerId": "account.969db62d37f04d218ae0a72ce539b23e", "revives": 0, "rideDistance": 0, "roadKills": 0, "swimDistance": 0, "teamKills": 0, "timeSurvived": 196, "vehicleDestroys": 0, "walkDistance": 242.98238, "weaponsAcquired": 5, "winPlace": 23}, "actor": ""}}, {"type": "participant", "id": "b452b32c-6df4-440f-a495-a8b190426f18", "attributes": {"actor": "", "shardId": "steam", "stats": {"DBNOs": 1, "assists": 1, "boosts": 7, "damageDealt": 143.68814, "deathType": "byplayer", "headshotKills": 0, "heals": 0, "killPlace": 32, "killStreaks": 1, "kills": 1, "longestKill": 4.3636827, "name": "00-hou-", "playerId": "account.12745dd54cb54deb96522ab79b1639fd", "revives": 1, "rideDistance": 4712.8374, "roadKills": 0, "swimDistance": 0, "teamKills": 0, "timeSurvived": 1003, "vehicleDestroys": 0, "walkDistance": 2002.4957, "weaponsAcquired": 7, "winPlace": 6}}}, {"type": "participant", "id": "6ca058b3-aa3c-4647-a89a-aeafae6e7e62", "attributes": {"stats": {"DBNOs": 1, "assists": 0, "boosts": 0, "damageDealt": 100, "deathType": "byplayer", "headshotKills": 0, "heals": 0, "killPlace": 49, "killStreaks": 1, "kills": 1, "longestKill": 12.953992, "name": "WoAIHeCococo", "playerId": "account.14c645d6880c423985a477452cd1929a", "revives": 0, "rideDistance": 0, "roadKills": 0, "swimDistance": 0, "teamKills": 0, "timeSurvived": 83, "vehicleDestroys": 0, "walkDistance": 45.92184, "weaponsAcquired": 1, "winPlace": 27}, "actor": "", "shardId": "steam"}}, {"type": "roster", "id": "45edb292-0555-44bb-b093-d8dc6051f0d4", "attributes": {"stats": {"rank": 3, "teamId": 28}, "won": "false", "shardId": "steam"}, "relationships": {"team": {"data": null}, "participants": {"data": [{"type": "participant", "id": "95874237-8e8b-4a5d-8190-394c22c57756"}, {"type": "participant", "id": "440d88b5-bcee-429e-bdb6-ad85b00a6035"}, {"type": "participant", "id": "e8cb7223-d942-48c1-816b-4884af88ae2d"}]}}}, {"type": "participant", "id": "b20ad24c-f905-45ae-a5cf-84d374edc738", "attributes": {"stats": {"DBNOs": 0, "assists": 0, "boosts": 5, "damageDealt": 58.868896, "deathType": "byplayer", "headshotKills": 0, "heals": 0, "killPlace": 53, "killStreaks": 0, "kills": 0, "longestKill": 0, "name": "CHENZHEdasb", "playerId": "account.f13283eb441d491db3a2876c18599c1a", "revives": 0, "rideDistance": 4257.4956, "roadKills": 0, "swimDistance": 0, "teamKills": 0, "timeSurvived": 717, "vehicleDestroys": 0, "walkDistance": 1331.4596, "weaponsAcquired": 9, "winPlace": 5}, "actor": "", "shardId": "steam"}}, {"type": "participant", "id": "ed5c629a-a4b2-4b47-acae-8cbe2312f983", "attributes": {"stats": {"DBNOs": 0, "assists": 0, "boosts": 2, "damageDealt": 63.863342, "deathType": "byplayer", "headshotKills": 0, "heals": 0, "killPlace": 80, "killStreaks": 0, "kills": 0, "longestKill": 0, "name": "886973", "playerId": "account.516b50f3f4db488caad965e58940213b", "revives": 0, "rideDistance": 0, "roadKills": 0, "swimDistance": 0, "teamKills": 0, "timeSurvived": 254, "vehicleDestroys": 0, "walkDistance": 494.17853, "weaponsAcquired": 7, "winPlace": 21}, "actor": "", "shardId": "steam"}}, {"type": "participant", "id": "608bf761-04b1-427b-9f22-ebce02a67ef5", "attributes": {"stats": {"DBNOs": 0, "assists": 2, "boosts": 0, "damageDealt": 88.38513, "deathType": "byplayer", "headshotKills": 0, "heals": 0, "killPlace": 72, "killStreaks": 0, "kills": 0, "longestKill": 0, "name": "4399_xoQ1", "playerId": "account.996e0e86aa534604877523bc2390df95", "revives": 3, "rideDistance": 0, "roadKills": 0, "swimDistance": 0, "teamKills": 0, "timeSurvived": 340, "vehicleDestroys": 0, "walkDistance": 584.99725, "weaponsAcquired": 3, "winPlace": 18}, "actor": "", "shardId": "steam"}}, {"type": "participant", "id": "0b502f6c-57b5-49e1-82de-76e610e02208", "attributes": {"stats": {"DBNOs": 1, "assists": 0, "boosts": 1, "damageDealt": 75, "deathType": "byplayer", "headshotKills": 0, "heals": 1, "killPlace": 37, "killStreaks": 1, "kills": 1, "longestKill": 56.08866, "name": "BB----999", "playerId": "account.0318b43182554a008ac853330486d5d9", "revives": 0, "rideDistance": 7290.6616, "roadKills": 0, "swimDistance": 0, "teamKills": 0, "timeSurvived": 771, "vehicleDestroys": 0, "walkDistance": 1595.6315, "weaponsAcquired": 8, "winPlace": 9}, "actor": "", "shardId": "steam"}}, {"type": "participant", "id": "b34d910d-5e42-4279-b893-1375ef51c754", "attributes": {"stats": {"DBNOs": 0, "assists": 0, "boosts": 0, "damageDealt": 0, "deathType": "byplayer", "headshotKills": 0, "heals": 0, "killPlace": 101, "killStreaks": 0, "kills": 0, "longestKill": 0, "name": "lencenaoly", "playerId": "account.ef5ca9963cca4e8a9cb9df02b5c35599", "revives": 0, "rideDistance": 0, "roadKills": 0, "swimDistance": 0, "teamKills": 0, "timeSurvived": 68, "vehicleDestroys": 0, "walkDistance": 21.43799, "weaponsAcquired": 1, "winPlace": 29}, "actor": "", "shardId": "steam"}}, {"type": "participant", "id": "c8cb97c2-a0a9-4e96-a1f4-f9e077830ac5", "attributes": {"stats": {"DBNOs": 0, "assists": 0, "boosts": 0, "damageDealt": 0, "deathType": "byplayer", "headshotKills": 0, "heals": 0, "killPlace": 100, "killStreaks": 0, "kills": 0, "longestKill": 0, "name": "bayfriend", "playerId": "account.9b30e115426e467aacdc7951dc6f575f", "revives": 0, "rideDistance": 0, "roadKills": 0, "swimDistance": 0, "teamKills": 0, "timeSurvived": 78, "vehicleDestroys": 0, "walkDistance": 44.769497, "weaponsAcquired": 1, "winPlace": 29}, "actor": "", "shardId": "steam"}}, {"type": "participant", "id": "e6c8b0ba-9aa0-48ce-9903-0bbcb70b86f6", "attributes": {"stats": {"DBNOs": 0, "assists": 2, "boosts": 1, "damageDealt": 40.230026, "deathType": "byplayer", "headshotKills": 0, "heals": 0, "killPlace": 58, "killStreaks": 0, "kills": 0, "longestKill": 0, "name": "LeslieMok", "playerId": "account.852cc71cbde14802bf4019d70154d37b", "revives": 0, "rideDistance": 1327.9225, "roadKills": 0, "swimDistance": 0, "teamKills": 0, "timeSurvived": 828, "vehicleDestroys": 0, "walkDistance": 1436.2888, "weaponsAcquired": 12, "winPlace": 11}, "actor": "", "shardId": "steam"}}, {"type": "roster", "id": "ef92b99e-57bc-4a20-bd67-351bb1bbe802", "attributes": {"won": "false", "shardId": "steam", "stats": {"rank": 18, "teamId": 6}}, "relationships": {"team": {"data": null}, "participants": {"data": [{"type": "participant", "id": "f5d916ab-1395-4d87-8547-51ff9b6d45af"}, {"type": "participant", "id": "66d5eb91-a369-4b25-ac0f-11f7b8af0bc0"}, {"type": "participant", "id": "75aa0b7f-d880-4604-8698-77f866df657f"}, {"type": "participant", "id": "608bf761-04b1-427b-9f22-ebce02a67ef5"}]}}}, {"type": "roster", "id": "c2800251-fe65-4295-acfc-c0520e0d63ac", "attributes": {"stats": {"rank": 23, "teamId": 17}, "won": "false", "shardId": "steam"}, "relationships": {"team": {"data": null}, "participants": {"data": [{"type": "participant", "id": "160e6a56-09a6-4351-a9c5-aa3e1ea2c8d2"}, {"type": "participant", "id": "6197436c-5ac9-4edf-b6ae-91459b19ae7e"}, {"type": "participant", "id": "fc04b721-4960-4e50-8327-8dff8be1ae15"}]}}}, {"type": "roster", "id": "9fbb5b20-bd1c-47e9-95d6-4097ba6b0d0b", "attributes": {"stats": {"rank": 22, "teamId": 16}, "won": "false", "shardId": "steam"}, "relationships": {"team": {"data": null}, "participants": {"data": [{"type": "participant", "id": "f3e090ff-af90-4b27-b358-49ed1cd01cb2"}, {"type": "participant", "id": "d6ca3576-689e-46c5-98a1-b52ddc3f7acc"}, {"type": "participant", "id": "b0b1c2a4-163c-479a-b438-47588996fb95"}]}}}, {"type": "participant", "id": "9793c772-0a1d-429c-9621-78386ca2a972", "attributes": {"stats": {"DBNOs": 1, "assists": 0, "boosts": 0, "damageDealt": 148.62985, "deathType": "byplayer", "headshotKills": 0, "heals": 0, "killPlace": 48, "killStreaks": 1, "kills": 1, "longestKill": 8.5615225, "name": "XuGuoHaoLa", "playerId": "account.b5ddd17a73344a01bb4dc74d4f8aa08e", "revives": 0, "rideDistance": 0, "roadKills": 0, "swimDistance": 0, "teamKills": 0, "timeSurvived": 136, "vehicleDestroys": 0, "walkDistance": 222.39142, "weaponsAcquired": 3, "winPlace": 27}, "actor": "", "shardId": "steam"}}, {"type": "participant", "id": "77351674-0212-4bea-afcc-276951c7bf46", "attributes": {"stats": {"DBNOs": 0, "assists": 0, "boosts": 0, "damageDealt": 39.630413, "deathType": "byplayer", "headshotKills": 0, "heals": 0, "killPlace": 67, "killStreaks": 0, "kills": 0, "longestKill": 0, "name": "WeJAn-", "playerId": "account.4c654e574bef47c2a4d3248ecf0b0bdb", "revives": 0, "rideDistance": 1327.2072, "roadKills": 0, "swimDistance": 0, "teamKills": 0, "timeSurvived": 407, "vehicleDestroys": 0, "walkDistance": 1089.3152, "weaponsAcquired": 6, "winPlace": 14}, "actor": "", "shardId": "steam"}}, {"type": "roster", "id": "40eb9588-c172-49ce-ac86-f76f11b636a9", "attributes": {"stats": {"rank": 1, "teamId": 12}, "won": "true", "shardId": "steam"}, "relationships": {"team": {"data": null}, "participants": {"data": [{"type": "participant", "id": "cec4ab1c-b38f-474c-938b-5fd72561c9f1"}, {"type": "participant", "id": "4b172636-3398-41bb-b334-9959288c9fb2"}, {"type": "participant", "id": "a965fad8-93b2-4b03-87f7-13a9efeee090"}, {"type": "participant", "id": "fe394a8a-dff8-4c31-b178-5f464c73de37"}]}}}, {"type": "participant", "id": "6be030de-12c2-4d60-9458-b76ede8b2942", "attributes": {"stats": {"DBNOs": 0, "assists": 0, "boosts": 0, "damageDealt": 234.13603, "deathType": "byplayer", "headshotKills": 0, "heals": 0, "killPlace": 88, "killStreaks": 0, "kills": 0, "longestKill": 0, "name": "MoLiang278", "playerId": "account.ce11b9c006be41c5a20e11ef7628678a", "revives": 0, "rideDistance": 0, "roadKills": 0, "swimDistance": 0, "teamKills": 0, "timeSurvived": 168, "vehicleDestroys": 0, "walkDistance": 373.7913, "weaponsAcquired": 5, "winPlace": 24}, "actor": "", "shardId": "steam"}}, {"type": "participant", "id": "1e95e5ff-8e44-440f-abfb-86e60caee1e2", "attributes": {"stats": {"DBNOs": 2, "assists": 2, "boosts": 5, "damageDealt": 227.19403, "deathType": "byzone", "headshotKills": 0, "heals": 9, "killPlace": 11, "killStreaks": 2, "kills": 3, "longestKill": 30.099157, "name": "Asgard--Loky", "playerId": "account.c6dbc99f8c90401d99e6ad0e489d3a73", "revives": 3, "rideDistance": 5406.097, "roadKills": 0, "swimDistance": 0, "teamKills": 0, "timeSurvived": 1065, "vehicleDestroys": 0, "walkDistance": 2335.8816, "weaponsAcquired": 12, "winPlace": 4}, "actor": "", "shardId": "steam"}}, {"type": "participant", "id": "f65dfa3b-2ceb-41fb-ae7e-684952fc5451", "attributes": {"stats": {"DBNOs": 1, "assists": 0, "boosts": 0, "damageDealt": 165.43478, "deathType": "byplayer", "headshotKills": 0, "heals": 0, "killPlace": 78, "killStreaks": 0, "kills": 0, "longestKill": 0, "name": "DawenXi-Xi", "playerId": "account.49827d964be3437cb5431ea0e3623f29", "revives": 0, "rideDistance": 0, "roadKills": 0, "swimDistance": 0, "teamKills": 0, "timeSurvived": 261, "vehicleDestroys": 0, "walkDistance": 427.31, "weaponsAcquired": 4, "winPlace": 21}, "actor": "", "shardId": "steam"}}, {"type": "roster", "id": "6e309304-d922-4c9b-ae3d-f2335352a2c3", "attributes": {"stats": {"rank": 9, "teamId": 18}, "won": "false", "shardId": "steam"}, "relationships": {"participants": {"data": [{"type": "participant", "id": "e0557373-e003-483c-8a3e-6539c8f1e7eb"}, {"type": "participant", "id": "0b502f6c-57b5-49e1-82de-76e610e02208"}, {"type": "participant", "id": "eac55399-f75a-4051-8cf7-aaafb376d3cb"}, {"type": "participant", "id": "e13a94e1-5394-49f9-8429-b563f88d901e"}]}, "team": {"data": null}}}, {"type": "roster", "id": "2402b2a1-83d6-45dc-91fc-f1c7aa4118e2", "attributes": {"shardId": "steam", "stats": {"rank": 24, "teamId": 19}, "won": "false"}, "relationships": {"team": {"data": null}, "participants": {"data": [{"type": "participant", "id": "d1c31911-dcbc-49e4-adc4-dd27b2a3b61c"}, {"type": "participant", "id": "6be030de-12c2-4d60-9458-b76ede8b2942"}, {"type": "participant", "id": "4d0c07c0-873b-4e1b-8ea2-a21927e42594"}]}}}, {"type": "participant", "id": "d1c31911-dcbc-49e4-adc4-dd27b2a3b61c", "attributes": {"stats": {"DBNOs": 1, "assists": 0, "boosts": 0, "damageDealt": 100, "deathType": "byplayer", "headshotKills": 0, "heals": 0, "killPlace": 89, "killStreaks": 0, "kills": 0, "longestKill": 0, "name": "dabiaoJJduan", "playerId": "account.07ffeeb6e254448aac7078d9c9a0c122", "revives": 0, "rideDistance": 0, "roadKills": 0, "swimDistance": 0, "teamKills": 0, "timeSurvived": 78, "vehicleDestroys": 0, "walkDistance": 36.160393, "weaponsAcquired": 1, "winPlace": 24}, "actor": "", "shardId": "steam"}}, {"type": "participant", "id": "58ef3272-3436-4978-8420-f35abc1578bb", "attributes": {"stats": {"DBNOs": 2, "assists": 2, "boosts": 9, "damageDealt": 578.76575, "deathType": "byplayer", "headshotKills": 0, "heals": 19, "killPlace": 9, "killStreaks": 1, "kills": 3, "longestKill": 113.70418, "name": "Tay1orSw1ft-13", "playerId": "account.e30d29c8515f4cb28891763f503779e8", "revives": 0, "rideDistance": 5461.0073, "roadKills": 0, "swimDistance": 0, "teamKills": 0, "timeSurvived": 1482, "vehicleDestroys": 0, "walkDistance": 2697.9065, "weaponsAcquired": 11, "winPlace": 2}, "actor": "", "shardId": "steam"}}, {"type": "participant", "id": "eac55399-f75a-4051-8cf7-aaafb376d3cb", "attributes": {"shardId": "steam", "stats": {"DBNOs": 0, "assists": 0, "boosts": 5, "damageDealt": 80, "deathType": "byplayer", "headshotKills": 1, "heals": 3, "killPlace": 36, "killStreaks": 1, "kills": 1, "longestKill": 4.9195013, "name": "weilaikkqq", "playerId": "account.df3c4f7ebec84bb2ac6e36ba400fa800", "revives": 0, "rideDistance": 7808.2627, "roadKills": 0, "swimDistance": 0, "teamKills": 0, "timeSurvived": 960, "vehicleDestroys": 0, "walkDistance": 1533.0437, "weaponsAcquired": 8, "winPlace": 9}, "actor": ""}}, {"type": "participant", "id": "95874237-8e8b-4a5d-8190-394c22c57756", "attributes": {"stats": {"DBNOs": 0, "assists": 0, "boosts": 8, "damageDealt": 0, "deathType": "byplayer", "headshotKills": 0, "heals": 2, "killPlace": 51, "killStreaks": 0, "kills": 0, "longestKill": 0, "name": "xiaohema_Pisces", "playerId": "account.b7191e4dc4264ca38327f08f6ab0dc13", "revives": 0, "rideDistance": 5547.4326, "roadKills": 0, "swimDistance": 0, "teamKills": 0, "timeSurvived": 1487, "vehicleDestroys": 0, "walkDistance": 2219.6414, "weaponsAcquired": 8, "winPlace": 3}, "actor": "", "shardId": "steam"}}, {"type": "participant", "id": "d677418d-c86f-43ed-8fe8-08458b0d512a", "attributes": {"actor": "", "shardId": "steam", "stats": {"DBNOs": 0, "assists": 0, "boosts": 0, "damageDealt": 0, "deathType": "byplayer", "headshotKills": 0, "heals": 0, "killPlace": 99, "killStreaks": 0, "kills": 0, "longestKill": 0, "name": "DaBiaoGe-xiao7", "playerId": "account.16b82178b1a24cf595c07700fa4ebe6a", "revives": 0, "rideDistance": 0, "roadKills": 0, "swimDistance": 0, "teamKills": 0, "timeSurvived": 94, "vehicleDestroys": 0, "walkDistance": 128.05177, "weaponsAcquired": 2, "winPlace": 29}}}, {"type": "participant", "id": "9a2241e0-b3f7-4302-8693-1341df3e57a1", "attributes": {"stats": {"DBNOs": 1, "assists": 0, "boosts": 1, "damageDealt": 70.12362, "deathType": "byplayer", "headshotKills": 0, "heals": 0, "killPlace": 73, "killStreaks": 0, "kills": 0, "longestKill": 0, "name": "Eternal-Lei", "playerId": "account.abe6ae933b404f589413c75a2c474303", "revives": 0, "rideDistance": 0, "roadKills": 0, "swimDistance": 0, "teamKills": 0, "timeSurvived": 277, "vehicleDestroys": 0, "walkDistance": 486.95648, "weaponsAcquired": 8, "winPlace": 19}, "actor": "", "shardId": "steam"}}, {"type": "participant", "id": "f3e090ff-af90-4b27-b358-49ed1cd01cb2", "attributes": {"stats": {"DBNOs": 0, "assists": 0, "boosts": 0, "damageDealt": 0, "deathType": "byplayer", "headshotKills": 0, "heals": 0, "killPlace": 84, "killStreaks": 0, "kills": 0, "longestKill": 0, "name": "GBRC-Aman", "playerId": "account.83053419ee9442008ff62e87c6952591", "revives": 0, "rideDistance": 0, "roadKills": 0, "swimDistance": 0, "teamKills": 0, "timeSurvived": 93, "vehicleDestroys": 0, "walkDistance": 19.017403, "weaponsAcquired": 1, "winPlace": 22}, "actor": "", "shardId": "steam"}}, {"type": "roster", "id": "6c530cc5-1d65-450d-99c4-00ca39765bcd", "attributes": {"stats": {"rank": 2, "teamId": 29}, "won": "false", "shardId": "steam"}, "relationships": {"team": {"data": null}, "participants": {"data": [{"type": "participant", "id": "d2b6f019-1266-4913-a7f9-bfcca95b500f"}, {"type": "participant", "id": "58ef3272-3436-4978-8420-f35abc1578bb"}, {"type": "participant", "id": "e3e11541-e4da-4b05-b6c4-3ce5487d105c"}]}}}, {"type": "participant", "id": "7408fc9b-3cf9-4782-bb32-4aa40ae0f00d", "attributes": {"stats": {"DBNOs": 1, "assists": 0, "boosts": 2, "damageDealt": 137.525, "deathType": "byplayer", "headshotKills": 0, "heals": 0, "killPlace": 68, "killStreaks": 0, "kills": 0, "longestKill": 0, "name": "DoyuTV-daboshen", "playerId": "account.faa3d2959023440ea2a29992899a8fae", "revives": 0, "rideDistance": 0, "roadKills": 0, "swimDistance": 0, "teamKills": 0, "timeSurvived": 376, "vehicleDestroys": 0, "walkDistance": 735.5216, "weaponsAcquired": 5, "winPlace": 15}, "actor": "", "shardId": "steam"}}, {"type": "participant", "id": "f5d916ab-1395-4d87-8547-51ff9b6d45af", "attributes": {"stats": {"DBNOs": 3, "assists": 0, "boosts": 1, "damageDealt": 270.494, "deathType": "byplayer", "headshotKills": 0, "heals": 8, "killPlace": 42, "killStreaks": 1, "kills": 1, "longestKill": 25.457586, "name": "Bo1ix", "playerId": "account.ca1c1653769f454a8f9b3f335ba40d17", "revives": 0, "rideDistance": 0, "roadKills": 0, "swimDistance": 0, "teamKills": 0, "timeSurvived": 340, "vehicleDestroys": 0, "walkDistance": 529.0055, "weaponsAcquired": 5, "winPlace": 18}, "actor": "", "shardId": "steam"}}, {"type": "participant", "id": "8bd720f3-0f37-421b-8a38-7941e92b5ae7", "attributes": {"actor": "", "shardId": "steam", "stats": {"DBNOs": 2, "assists": 1, "boosts": 9, "damageDealt": 220.2911, "deathType": "byzone", "headshotKills": 0, "heals": 5, "killPlace": 18, "killStreaks": 1, "kills": 2, "longestKill": 9.832981, "name": "ab_6951", "playerId": "account.81ec953396e944fbb69e3f972215b886", "revives": 0, "rideDistance": 4233.363, "roadKills": 0, "swimDistance": 0, "teamKills": 0, "timeSurvived": 1172, "vehicleDestroys": 0, "walkDistance": 2463.3787, "weaponsAcquired": 13, "winPlace": 5}}}, {"type": "participant", "id": "66d5eb91-a369-4b25-ac0f-11f7b8af0bc0", "attributes": {"stats": {"DBNOs": 1, "assists": 1, "boosts": 1, "damageDealt": 260, "deathType": "byplayer", "headshotKills": 0, "heals": 0, "killPlace": 26, "killStreaks": 1, "kills": 2, "longestKill": 3.726702, "name": "Yo1o-", "playerId": "account.16c236ec60674554ae84dffce448286d", "revives": 1, "rideDistance": 0, "roadKills": 0, "swimDistance": 0, "teamKills": 0, "timeSurvived": 316, "vehicleDestroys": 0, "walkDistance": 526.1744, "weaponsAcquired": 6, "winPlace": 18}, "actor": "", "shardId": "steam"}}, {"type": "participant", "id": "914f555f-48d6-48cc-a037-bebaa3403032", "attributes": {"stats": {"DBNOs": 0, "assists": 0, "boosts": 4, "damageDealt": 60.69366, "deathType": "byplayer", "headshotKills": 0, "heals": 0, "killPlace": 57, "killStreaks": 0, "kills": 0, "longestKill": 0, "name": "BravoTeam-Father", "playerId": "account.08a3d507230a48dea9ef432fd8b137d6", "revives": 0, "rideDistance": 5205.4707, "roadKills": 0, "swimDistance": 0, "teamKills": 0, "timeSurvived": 757, "vehicleDestroys": 0, "walkDistance": 1192.1461, "weaponsAcquired": 13, "winPlace": 10}, "actor": "", "shardId": "steam"}}, {"type": "participant", "id": "b59bf495-9352-46a3-a12f-914eb9869715", "attributes": {"actor": "", "shardId": "steam", "stats": {"DBNOs": 0, "assists": 0, "boosts": 0, "damageDealt": 0, "deathType": "byplayer", "headshotKills": 0, "heals": 0, "killPlace": 95, "killStreaks": 0, "kills": 0, "longestKill": 0, "name": "Ruige_2025", "playerId": "account.4b29a2850eab4204842d53f775d06a40", "revives": 0, "rideDistance": 0, "roadKills": 0, "swimDistance": 0, "teamKills": 0, "timeSurvived": 136, "vehicleDestroys": 0, "walkDistance": 73.36908, "weaponsAcquired": 2, "winPlace": 27}}}, {"type": "participant", "id": "287cba64-fdf5-4cb4-abae-8419f578dbe8", "attributes": {"stats": {"DBNOs": 0, "assists": 0, "boosts": 2, "damageDealt": 73.2, "deathType": "byplayer", "headshotKills": 0, "heals": 0, "killPlace": 66, "killStreaks": 0, "kills": 0, "longestKill": 0, "name": "hyx357951", "playerId": "account.a9d72658334346e486ccb0e2b1e17f87", "revives": 0, "rideDistance": 1845.5056, "roadKills": 0, "swimDistance": 0, "teamKills": 0, "timeSurvived": 437, "vehicleDestroys": 0, "walkDistance": 789.3248, "weaponsAcquired": 6, "winPlace": 14}, "actor": "", "shardId": "steam"}}, {"type": "roster", "id": "6a9b0903-f946-4716-8b4d-fb38778e1872", "attributes": {"stats": {"rank": 15, "teamId": 3}, "won": "false", "shardId": "steam"}, "relationships": {"team": {"data": null}, "participants": {"data": [{"type": "participant", "id": "30d67a9e-833c-4584-b4dc-49c0d6e8de60"}, {"type": "participant", "id": "ed5c629a-a4b2-4b47-acae-8cbe2312f983"}, {"type": "participant", "id": "7408fc9b-3cf9-4782-bb32-4aa40ae0f00d"}, {"type": "participant", "id": "dca472b6-5ea0-417e-aed3-a3b1ea522ec7"}]}}}, {"type": "roster", "id": "ea95686d-81d3-484a-b3c4-8b4e4facc242", "attributes": {"won": "false", "shardId": "steam", "stats": {"rank": 11, "teamId": 5}}, "relationships": {"team": {"data": null}, "participants": {"data": [{"type": "participant", "id": "e33133dd-22c0-495d-8cf2-9621404d36e7"}, {"type": "participant", "id": "32bcd07e-02b6-4801-8400-2cfb2a130fca"}, {"type": "participant", "id": "e6c8b0ba-9aa0-48ce-9903-0bbcb70b86f6"}, {"type": "participant", "id": "79c7ad61-30a6-4279-bc94-46056b39eec5"}]}}}, {"type": "participant", "id": "57368a7f-dd17-4996-8237-76c0ccb139a8", "attributes": {"stats": {"DBNOs": 3, "assists": 1, "boosts": 3, "damageDealt": 341.94443, "deathType": "byplayer", "headshotKills": 0, "heals": 3, "killPlace": 12, "killStreaks": 1, "kills": 3, "longestKill": 18.397907, "name": "Roverer", "playerId": "account.93ac3d85636b416282e03c22f9396dfc", "revives": 0, "rideDistance": 4232.3374, "roadKills": 0, "swimDistance": 0, "teamKills": 0, "timeSurvived": 845, "vehicleDestroys": 0, "walkDistance": 1550.883, "weaponsAcquired": 14, "winPlace": 5}, "actor": "", "shardId": "steam"}}, {"type": "participant", "id": "30d67a9e-833c-4584-b4dc-49c0d6e8de60", "attributes": {"actor": "", "shardId": "steam", "stats": {"DBNOs": 1, "assists": 0, "boosts": 2, "damageDealt": 112.590546, "deathType": "byplayer", "headshotKills": 1, "heals": 0, "killPlace": 40, "killStreaks": 1, "kills": 1, "longestKill": 41.170826, "name": "THE-AK-47-A", "playerId": "account.b828a85e21e64fadba6b98e63ee85c50", "revives": 0, "rideDistance": 0, "roadKills": 0, "swimDistance": 0, "teamKills": 0, "timeSurvived": 376, "vehicleDestroys": 0, "walkDistance": 620.3094, "weaponsAcquired": 8, "winPlace": 15}}}, {"type": "participant", "id": "e2b323da-3463-4ed2-8540-59c976ebae68", "attributes": {"stats": {"DBNOs": 0, "assists": 0, "boosts": 0, "damageDealt": 65.79, "deathType": "byplayer", "headshotKills": 0, "heals": 0, "killPlace": 98, "killStreaks": 0, "kills": 0, "longestKill": 0, "name": "skuchiyaer", "playerId": "account.64c86f7d06da4c03bfbbfcb872345104", "revives": 0, "rideDistance": 0, "roadKills": 0, "swimDistance": 0, "teamKills": 0, "timeSurvived": 76, "vehicleDestroys": 0, "walkDistance": 43.44743, "weaponsAcquired": 2, "winPlace": 28}, "actor": "", "shardId": "steam"}}, {"type": "roster", "id": "b5d05d90-bab1-46e0-8934-a3e0a3c0b654", "attributes": {"stats": {"rank": 14, "teamId": 26}, "won": "false", "shardId": "steam"}, "relationships": {"participants": {"data": [{"type": "participant", "id": "287cba64-fdf5-4cb4-abae-8419f578dbe8"}, {"type": "participant", "id": "77351674-0212-4bea-afcc-276951c7bf46"}, {"type": "participant", "id": "287864c8-eeb8-492f-af75-099812958c92"}]}, "team": {"data": null}}}, {"type": "participant", "id": "fb0ae12c-bb0e-45f3-88fe-cb22113919ac", "attributes": {"stats": {"DBNOs": 0, "assists": 1, "boosts": 4, "damageDealt": 0, "deathType": "byplayer", "headshotKills": 0, "heals": 1, "killPlace": 56, "killStreaks": 0, "kills": 0, "longestKill": 0, "name": "Sh1real_", "playerId": "account.13c7fa16229446b89176e37ad149673b", "revives": 0, "rideDistance": 5322.852, "roadKills": 0, "swimDistance": 0, "teamKills": 0, "timeSurvived": 845, "vehicleDestroys": 0, "walkDistance": 1292.1605, "weaponsAcquired": 9, "winPlace": 10}, "actor": "", "shardId": "steam"}}, {"type": "participant", "id": "9f0c27a0-595f-46b2-97a0-57c280cb09ed", "attributes": {"stats": {"DBNOs": 0, "assists": 0, "boosts": 0, "damageDealt": 0, "deathType": "byplayer", "headshotKills": 0, "heals": 0, "killPlace": 94, "killStreaks": 0, "kills": 0, "longestKill": 0, "name": "woaishenhe-", "playerId": "account.0d4bce716c3546f0a43846a9ccb7a7fe", "revives": 0, "rideDistance": 0, "roadKills": 0, "swimDistance": 0, "teamKills": 0, "timeSurvived": 85, "vehicleDestroys": 0, "walkDistance": 25.465982, "weaponsAcquired": 1, "winPlace": 26}, "actor": "", "shardId": "steam"}}, {"type": "roster", "id": "e45d484d-3568-4611-8fcf-0e443023f232", "attributes": {"stats": {"rank": 5, "teamId": 23}, "won": "false", "shardId": "steam"}, "relationships": {"team": {"data": null}, "participants": {"data": [{"type": "participant", "id": "860bcfe3-9b43-421e-b35b-a18013567741"}, {"type": "participant", "id": "8bd720f3-0f37-421b-8a38-7941e92b5ae7"}, {"type": "participant", "id": "b20ad24c-f905-45ae-a5cf-84d374edc738"}, {"type": "participant", "id": "57368a7f-dd17-4996-8237-76c0ccb139a8"}]}}}, {"type": "roster", "id": "41150ef3-9d04-4eea-9ad2-b9f539dd511b", "attributes": {"stats": {"rank": 17, "teamId": 24}, "won": "false", "shardId": "steam"}, "relationships": {"team": {"data": null}, "participants": {"data": [{"type": "participant", "id": "9a102e56-8208-44f4-952c-6b28fbeec41c"}, {"type": "participant", "id": "11496ceb-bfc8-4c32-a4b2-16e2144408c8"}, {"type": "participant", "id": "1678036e-f785-419e-bafd-4ff684836eca"}]}}}, {"type": "participant", "id": "2a992e7b-1757-43bb-84ef-cdb88a242e8d", "attributes": {"stats": {"DBNOs": 5, "assists": 2, "boosts": 9, "damageDealt": 776.46326, "deathType": "byplayer", "headshotKills": 1, "heals": 5, "killPlace": 1, "killStreaks": 2, "kills": 6, "longestKill": 21.954538, "name": "Rtasyagopa", "playerId": "account.3ea8bd5e4bee4306879c13fe4d4cae34", "revives": 1, "rideDistance": 3644.0974, "roadKills": 0, "swimDistance": 0, "teamKills": 0, "timeSurvived": 1037, "vehicleDestroys": 0, "walkDistance": 1973.6971, "weaponsAcquired": 12, "winPlace": 7}, "actor": "", "shardId": "steam"}}, {"type": "participant", "id": "440d88b5-bcee-429e-bdb6-ad85b00a6035", "attributes": {"shardId": "steam", "stats": {"DBNOs": 1, "assists": 0, "boosts": 9, "damageDealt": 99.999985, "deathType": "byplayer", "headshotKills": 0, "heals": 1, "killPlace": 30, "killStreaks": 1, "kills": 1, "longestKill": 61.982773, "name": "Wmister-Roy121", "playerId": "account.77946938f4424df196f82982de50e6a8", "revives": 0, "rideDistance": 5360.051, "roadKills": 0, "swimDistance": 0, "teamKills": 0, "timeSurvived": 1473, "vehicleDestroys": 0, "walkDistance": 3143.3962, "weaponsAcquired": 18, "winPlace": 3}, "actor": ""}}, {"type": "participant", "id": "b74b8085-bc7d-4bbc-8684-32a1201c774e", "attributes": {"actor": "", "shardId": "steam", "stats": {"DBNOs": 0, "assists": 1, "boosts": 6, "damageDealt": 194.87779, "deathType": "byplayer", "headshotKills": 0, "heals": 2, "killPlace": 21, "killStreaks": 1, "kills": 2, "longestKill": 42.70916, "name": "1o9o_e", "playerId": "account.16b2cd196511428aaa0f5a6fc604536e", "revives": 0, "rideDistance": 6530.5947, "roadKills": 0, "swimDistance": 0, "teamKills": 0, "timeSurvived": 1000, "vehicleDestroys": 0, "walkDistance": 1785.1365, "weaponsAcquired": 11, "winPlace": 8}}}, {"type": "participant", "id": "1a55de3f-eb84-479d-8892-843019ae3b26", "attributes": {"stats": {"DBNOs": 0, "assists": 0, "boosts": 0, "damageDealt": 0, "deathType": "byplayer", "headshotKills": 0, "heals": 0, "killPlace": 62, "killStreaks": 0, "kills": 0, "longestKill": 0, "name": "EYESO_JAY", "playerId": "account.ea986c07ebba430ab3a5cba6e2c6c706", "revives": 0, "rideDistance": 0, "roadKills": 0, "swimDistance": 0, "teamKills": 0, "timeSurvived": 317, "vehicleDestroys": 0, "walkDistance": 493.64423, "weaponsAcquired": 8, "winPlace": 12}, "actor": "", "shardId": "steam"}}, {"type": "roster", "id": "843c3799-078c-462b-838e-7c69ae95b8fb", "attributes": {"stats": {"rank": 19, "teamId": 27}, "won": "false", "shardId": "steam"}, "relationships": {"team": {"data": null}, "participants": {"data": [{"type": "participant", "id": "9a2241e0-b3f7-4302-8693-1341df3e57a1"}, {"type": "participant", "id": "fbc53ad0-55a2-4d67-bcb6-c039cc868d58"}, {"type": "participant", "id": "4302b91c-ecdd-4cf2-b883-000a77c4d052"}]}}}, {"type": "asset", "id": "7dfb5b4e-ea47-11f0-9046-e6c087f7d05a", "attributes": {"URL": "https://telemetry-cdn.pubg.com/bluehole-pubg/steam/2026/01/05/15/02/7dfb5b4e-ea47-11f0-9046-e6c087f7d05a-telemetry.json", "name": "telemetry", "description": "", "createdAt": "2026-01-05T15:02:02Z"}}, {"type": "participant", "id": "fe394a8a-dff8-4c31-b178-5f464c73de37", "attributes": {"stats": {"DBNOs": 1, "assists": 1, "boosts": 7, "damageDealt": 420.8903, "deathType": "alive", "headshotKills": 1, "heals": 0, "killPlace": 27, "killStreaks": 1, "kills": 1, "longestKill": 183.5118, "name": "Lhy666118", "playerId": "account.1c034a193be145b493cb1be28eb78759", "revives": 0, "rideDistance": 8099.4404, "roadKills": 0, "swimDistance": 0, "teamKills": 0, "timeSurvived": 1554, "vehicleDestroys": 0, "walkDistance": 3416.9812, "weaponsAcquired": 10, "winPlace": 1}, "actor": "", "shardId": "steam"}}, {"type": "participant", "id": "75aa0b7f-d880-4604-8698-77f866df657f", "attributes": {"shardId": "steam", "stats": {"DBNOs": 5, "assists": 0, "boosts": 4, "damageDealt": 512.7086, "deathType": "byplayer", "headshotKills": 0, "heals": 2, "killPlace": 4, "killStreaks": 2, "kills": 5, "longestKill": 20.19921, "name": "7ioku_", "playerId": "account.cc02a37329da4dd796df3151bb08eb46", "revives": 0, "rideDistance": 0, "roadKills": 0, "swimDistance": 0, "teamKills": 0, "timeSurvived": 327, "vehicleDestroys": 0, "walkDistance": 488.97006, "weaponsAcquired": 4, "winPlace": 18}, "actor": ""}}, {"type": "participant", "id": "8ad21d1a-1f19-4060-b905-042c761098ca", "attributes": {"stats": {"DBNOs": 5, "assists": 3, "boosts": 11, "damageDealt": 321.57983, "deathType": "byplayer", "headshotKills": 2, "heals": 13, "killPlace": 2, "killStreaks": 2, "kills": 5, "longestKill": 66.99619, "name": "calligraphers", "playerId": "account.549bd2c88379469c873635e3cee635e2", "revives": 0, "rideDistance": 6393.836, "roadKills": 0, "swimDistance": 0, "teamKills": 0, "timeSurvived": 1182, "vehicleDestroys": 0, "walkDistance": 2692.231, "weaponsAcquired": 10, "winPlace": 4}, "actor": "", "shardId": "steam"}}, {"type": "participant", "id": "11496ceb-bfc8-4c32-a4b2-16e2144408c8", "attributes": {"stats": {"DBNOs": 2, "assists": 0, "boosts": 3, "damageDealt": 319.36002, "deathType": "byplayer", "headshotKills": 1, "heals": 1, "killPlace": 41, "killStreaks": 1, "kills": 1, "longestKill": 7.4470606, "name": "TaoG-Ge-1v4", "playerId": "account.b273dd405d2a46e8a71229d5ab47ed88", "revives": 0, "rideDistance": 0, "roadKills": 0, "swimDistance": 0, "teamKills": 0, "timeSurvived": 345, "vehicleDestroys": 0, "walkDistance": 550.149, "weaponsAcquired": 5, "winPlace": 17}, "actor": "", "shardId": "steam"}}, {"type": "roster", "id": "df9c592a-a8bf-4470-a9a9-bb11ded1e147", "attributes": {"stats": {"rank": 8, "teamId": 8}, "won": "false", "shardId": "steam"}, "relationships": {"team": {"data": null}, "participants": {"data": [{"type": "participant", "id": "a4bd780f-7405-463e-8f69-ca28a1f61554"}, {"type": "participant", "id": "5b703b4b-80f5-4bfb-aa18-86dff9efdd20"}, {"type": "participant", "id": "b74b8085-bc7d-4bbc-8684-32a1201c774e"}]}}}, {"type": "roster", "id": "f83a0f78-96e7-418a-8046-2aeadafbc5bd", "attributes": {"stats": {"rank": 25, "teamId": 25}, "won": "false", "shardId": "steam"}, "relationships": {"team": {"data": null}, "participants": {"data": [{"type": "participant", "id": "90b05e12-3d6a-4c59-be33-5caecae2cb17"}, {"type": "participant", "id": "4374f78a-0462-43e8-9b0f-a7c0682a45bb"}, {"type": "participant", "id": "15271408-4272-47e8-97b5-1d18430c6f97"}]}}}, {"type": "participant", "id": "4d0c07c0-873b-4e1b-8ea2-a21927e42594", "attributes": {"actor": "", "shardId": "steam", "stats": {"DBNOs": 1, "assists": 0, "boosts": 0, "damageDealt": 100, "deathType": "byplayer", "headshotKills": 1, "heals": 0, "killPlace": 45, "killStreaks": 1, "kills": 1, "longestKill": 7.245135, "name": "C0wH", "playerId": "account.59c9e5f2f9f24404abd3e7028c594a77", "revives": 0, "rideDistance": 0, "roadKills": 0, "swimDistance": 0, "teamKills": 0, "timeSurvived": 97, "vehicleDestroys": 0, "walkDistance": 105.30209, "weaponsAcquired": 2, "winPlace": 24}}}, {"type": "participant", "id": "a81b99cd-2e68-474c-b3a9-ab770730ff1c", "attributes": {"stats": {"DBNOs": 0, "assists": 0, "boosts": 0, "damageDealt": 58.24588, "deathType": "byplayer", "headshotKills": 0, "heals": 0, "killPlace": 91, "killStreaks": 0, "kills": 0, "longestKill": 0, "name": "YOYOBABY98", "playerId": "account.d4475d5c0b7c4640ba369846a1dee848", "revives": 0, "rideDistance": 0, "roadKills": 0, "swimDistance": 0, "teamKills": 0, "timeSurvived": 149, "vehicleDestroys": 0, "walkDistance": 179.12305, "weaponsAcquired": 2, "winPlace": 26}, "actor": "", "shardId": "steam"}}, {"type": "roster", "id": "dc4f6f44-8885-4b05-85e1-52f7eb565488", "attributes": {"stats": {"rank": 4, "teamId": 21}, "won": "false", "shardId": "steam"}, "relationships": {"participants": {"data": [{"type": "participant", "id": "1e95e5ff-8e44-440f-abfb-86e60caee1e2"}, {"type": "participant", "id": "e6c1c11d-b0a5-4363-9dd4-40cbc8445f47"}, {"type": "participant", "id": "8ad21d1a-1f19-4060-b905-042c761098ca"}, {"type": "participant", "id": "c2cf7a32-2942-46cc-ac1a-c47689661f25"}]}, "team": {"data": null}}}, {"type": "participant", "id": "58a604ec-55f2-4f16-a7e1-534d2a3c6a6f", "attributes": {"shardId": "steam", "stats": {"DBNOs": 3, "assists": 1, "boosts": 0, "damageDealt": 369.67426, "deathType": "byplayer", "headshotKills": 0, "heals": 0, "killPlace": 7, "killStreaks": 1, "kills": 4, "longestKill": 44.957043, "name": "B-e-MySucker", "playerId": "account.3b6d91455fec40f18af384545706cfab", "revives": 0, "rideDistance": 0, "roadKills": 0, "swimDistance": 0, "teamKills": 0, "timeSurvived": 298, "vehicleDestroys": 0, "walkDistance": 512.84753, "weaponsAcquired": 7, "winPlace": 16}, "actor": ""}}, {"type": "participant", "id": "e762af82-c6cc-42e9-bd6d-881f8475cd08", "attributes": {"stats": {"DBNOs": 1, "assists": 1, "boosts": 3, "damageDealt": 333.175, "deathType": "byplayer", "headshotKills": 0, "heals": 2, "killPlace": 24, "killStreaks": 2, "kills": 2, "longestKill": 34.090298, "name": "zhishishaoji", "playerId": "account.e0ac87eaac054b2cb75cfc8264d11773", "revives": 0, "rideDistance": 0, "roadKills": 0, "swimDistance": 0, "teamKills": 0, "timeSurvived": 374, "vehicleDestroys": 0, "walkDistance": 765.16864, "weaponsAcquired": 6, "winPlace": 16}, "actor": "", "shardId": "steam"}}, {"type": "participant", "id": "1678036e-f785-419e-bafd-4ff684836eca", "attributes": {"actor": "", "shardId": "steam", "stats": {"DBNOs": 0, "assists": 0, "boosts": 0, "damageDealt": 0, "deathType": "byplayer", "headshotKills": 0, "heals": 0, "killPlace": 71, "killStreaks": 0, "kills": 0, "longestKill": 0, "name": "Hello-GG_OvO", "playerId": "account.48ca776cd7fa431b85cf3e2ddf425d06", "revives": 0, "rideDistance": 0, "roadKills": 0, "swimDistance": 0, "teamKills": 0, "timeSurvived": 75, "vehicleDestroys": 0, "walkDistance": 87.747314, "weaponsAcquired": 1, "winPlace": 17}}}, {"type": "participant", "id": "d39e2e96-5204-423e-8a52-c494eb5f8b26", "attributes": {"stats": {"DBNOs": 0, "assists": 1, "boosts": 9, "damageDealt": 299.94775, "deathType": "byplayer", "headshotKills": 1, "heals": 1, "killPlace": 19, "killStreaks": 1, "kills": 2, "longestKill": 160.21777, "name": "Meet_Ye", "playerId": "account.27380b0517a64714bd087d72ffcd7e76", "revives": 0, "rideDistance": 5001.331, "roadKills": 0, "swimDistance": 0, "teamKills": 0, "timeSurvived": 1083, "vehicleDestroys": 0, "walkDistance": 2129.4602, "weaponsAcquired": 13, "winPlace": 6}, "actor": "", "shardId": "steam"}}, {"type": "participant", "id": "15271408-4272-47e8-97b5-1d18430c6f97", "attributes": {"stats": {"DBNOs": 1, "assists": 0, "boosts": 0, "damageDealt": 100, "deathType": "byplayer", "headshotKills": 0, "heals": 0, "killPlace": 47, "killStreaks": 1, "kills": 1, "longestKill": 6.202221, "name": "MYT_AWiGG", "playerId": "account.c0126cdc7eb9414085d8add374855df3", "revives": 0, "rideDistance": 0, "roadKills": 0, "swimDistance": 0, "teamKills": 0, "timeSurvived": 82, "vehicleDestroys": 0, "walkDistance": 90.21819, "weaponsAcquired": 1, "winPlace": 25}, "actor": "", "shardId": "steam"}}, {"type": "participant", "id": "90bc8203-dced-40bc-8cb1-769c93d7cfae", "attributes": {"stats": {"DBNOs": 0, "assists": 0, "boosts": 0, "damageDealt": 0, "deathType": "byplayer", "headshotKills": 0, "heals": 0, "killPlace": 96, "killStreaks": 0, "kills": 0, "longestKill": 0, "name": "Douyu-5832816", "playerId": "account.c2f40148381e4ab5bec60840160364c1", "revives": 1, "rideDistance": 0, "roadKills": 0, "swimDistance": 0, "teamKills": 0, "timeSurvived": 136, "vehicleDestroys": 0, "walkDistance": 196.54915, "weaponsAcquired": 3, "winPlace": 27}, "actor": "", "shardId": "steam"}}, {"type": "participant", "id": "cec4ab1c-b38f-474c-938b-5fd72561c9f1", "attributes": {"stats": {"DBNOs": 0, "assists": 0, "boosts": 3, "damageDealt": 23.735355, "deathType": "byplayer", "headshotKills": 1, "heals": 1, "killPlace": 29, "killStreaks": 1, "kills": 1, "longestKill": 59.654495, "name": "XXL0020", "playerId": "account.639f19f984fb4ce581ac7b5fdfb0487a", "revives": 0, "rideDistance": 4415.0015, "roadKills": 0, "swimDistance": 0, "teamKills": 0, "timeSurvived": 1322, "vehicleDestroys": 0, "walkDistance": 2957.99, "weaponsAcquired": 15, "winPlace": 1}, "actor": "", "shardId": "steam"}}, {"type": "participant", "id": "44f4d062-8ace-4819-a4ab-ee8542829a1c", "attributes": {"stats": {"DBNOs": 3, "assists": 0, "boosts": 0, "damageDealt": 300, "deathType": "byplayer", "headshotKills": 0, "heals": 0, "killPlace": 15, "killStreaks": 2, "kills": 3, "longestKill": 5.866687, "name": "3pvashq", "playerId": "account.d1efd150efed4c9ea8c4ffa8d66a9369", "revives": 0, "rideDistance": 0, "roadKills": 0, "swimDistance": 0, "teamKills": 0, "timeSurvived": 116, "vehicleDestroys": 0, "walkDistance": 145.1163, "weaponsAcquired": 3, "winPlace": 28}, "actor": "", "shardId": "steam"}}, {"type": "roster", "id": "13f2450f-62ff-4f90-b685-224e7d495ccd", "attributes": {"shardId": "steam", "stats": {"rank": 6, "teamId": 15}, "won": "false"}, "relationships": {"team": {"data": null}, "participants": {"data": [{"type": "participant", "id": "0f383a3e-67ba-44a6-b905-b60f358d2b81"}, {"type": "participant", "id": "d39e2e96-5204-423e-8a52-c494eb5f8b26"}, {"type": "participant", "id": "b452b32c-6df4-440f-a495-a8b190426f18"}]}}}, {"type": "participant", "id": "c8e19613-2000-41d3-8091-937fef46a8ac", "attributes": {"stats": {"DBNOs": 1, "assists": 0, "boosts": 5, "damageDealt": 100.000015, "deathType": "byplayer", "headshotKills": 0, "heals": 0, "killPlace": 34, "killStreaks": 1, "kills": 1, "longestKill": 10.144895, "name": "TTccnn22", "playerId": "account.ba40434aaf644b079f493d588dd09a63", "revives": 0, "rideDistance": 810.15375, "roadKills": 0, "swimDistance": 0, "teamKills": 0, "timeSurvived": 806, "vehicleDestroys": 0, "walkDistance": 1473.585, "weaponsAcquired": 7, "winPlace": 7}, "actor": "", "shardId": "steam"}}, {"type": "participant", "id": "4dd0f11c-5291-4331-a019-4fa98caa08fc", "attributes": {"stats": {"DBNOs": 1, "assists": 0, "boosts": 1, "damageDealt": 142.67957, "deathType": "byplayer", "headshotKills": 0, "heals": 1, "killPlace": 33, "killStreaks": 1, "kills": 1, "longestKill": 8.072832, "name": "happy_TuTuMiao", "playerId": "account.005ff8cbcc4c4c44a2e3f838994429a7", "revives": 1, "rideDistance": 3615.2766, "roadKills": 0, "swimDistance": 0, "teamKills": 0, "timeSurvived": 1020, "vehicleDestroys": 0, "walkDistance": 1799.3971, "weaponsAcquired": 6, "winPlace": 7}, "actor": "", "shardId": "steam"}}, {"type": "participant", "id": "cafb2c70-ddbb-44ce-b1b3-8b6f19d74cf0", "attributes": {"stats": {"DBNOs": 0, "assists": 0, "boosts": 2, "damageDealt": 89.55276, "deathType": "byplayer", "headshotKills": 0, "heals": 2, "killPlace": 74, "killStreaks": 0, "kills": 0, "longestKill": 0, "name": "jonghun3319", "playerId": "account.3f82ce5a9973432cb5c0152a01756933", "revives": 0, "rideDistance": 0, "roadKills": 0, "swimDistance": 0, "teamKills": 0, "timeSurvived": 318, "vehicleDestroys": 0, "walkDistance": 419.8816, "weaponsAcquired": 6, "winPlace": 20}, "actor": "", "shardId": "steam"}}, {"type": "participant", "id": "0a2f20f8-640f-4da2-9074-5b78c3b42f5f", "attributes": {"shardId": "steam", "stats": {"DBNOs": 0, "assists": 0, "boosts": 0, "damageDealt": 0, "deathType": "byplayer", "headshotKills": 0, "heals": 0, "killPlace": 75, "killStreaks": 0, "kills": 0, "longestKill": 0, "name": "sujin__11", "playerId": "account.c29da8c746454d1fb261221d79ee539a", "revives": 0, "rideDistance": 0, "roadKills": 0, "swimDistance": 0, "teamKills": 0, "timeSurvived": 214, "vehicleDestroys": 0, "walkDistance": 280.37625, "weaponsAcquired": 5, "winPlace": 20}, "actor": ""}}, {"type": "participant", "id": "e3e11541-e4da-4b05-b6c4-3ce5487d105c", "attributes": {"stats": {"DBNOs": 2, "assists": 2, "boosts": 10, "damageDealt": 440.16238, "deathType": "byplayer", "headshotKills": 0, "heals": 11, "killPlace": 8, "killStreaks": 2, "kills": 3, "longestKill": 100.77247, "name": "Aiown-", "playerId": "account.fb2930ba89834ba2a36d627d04736e0d", "revives": 0, "rideDistance": 3412.2854, "roadKills": 0, "swimDistance": 0, "teamKills": 0, "timeSurvived": 1551, "vehicleDestroys": 0, "walkDistance": 3381.6123, "weaponsAcquired": 18, "winPlace": 2}, "actor": "", "shardId": "steam"}}, {"type": "participant", "id": "68f2d427-0dca-4409-85c6-e423b9f9ecc1", "attributes": {"stats": {"DBNOs": 1, "assists": 0, "boosts": 3, "damageDealt": 189.33455, "deathType": "byplayer", "headshotKills": 0, "heals": 5, "killPlace": 23, "killStreaks": 1, "kills": 2, "longestKill": 9.504631, "name": "zhugxuoqngh", "playerId": "account.805a07f052ba422395d14a4c13560623", "revives": 0, "rideDistance": 5493.78, "roadKills": 0, "swimDistance": 0, "teamKills": 0, "timeSurvived": 726, "vehicleDestroys": 0, "walkDistance": 1313.8552, "weaponsAcquired": 12, "winPlace": 12}, "actor": "", "shardId": "steam"}}, {"type": "participant", "id": "0f383a3e-67ba-44a6-b905-b60f358d2b81", "attributes": {"stats": {"DBNOs": 5, "assists": 0, "boosts": 9, "damageDealt": 382.2306, "deathType": "byplayer", "headshotKills": 2, "heals": 3, "killPlace": 6, "killStreaks": 2, "kills": 4, "longestKill": 151.85326, "name": "DokiStarr", "playerId": "account.61234160ca8e4598aed5feb0a3a3c74b", "revives": 1, "rideDistance": 4319.7144, "roadKills": 0, "swimDistance": 0, "teamKills": 0, "timeSurvived": 1074, "vehicleDestroys": 0, "walkDistance": 2533.7224, "weaponsAcquired": 11, "winPlace": 6}, "actor": "", "shardId": "steam"}}, {"type": "roster", "id": "4178bff3-cc7b-4725-a10e-7638784d0910", "attributes": {"stats": {"rank": 12, "teamId": 4}, "won": "false", "shardId": "steam"}, "relationships": {"team": {"data": null}, "participants": {"data": [{"type": "participant", "id": "0825ccc6-a9d5-460b-9339-c4a9bf694ce0"}, {"type": "participant", "id": "6a5d79d3-c0fa-4044-bea1-20fca67672da"}, {"type": "participant", "id": "68f2d427-0dca-4409-85c6-e423b9f9ecc1"}, {"type": "participant", "id": "1a55de3f-eb84-479d-8892-843019ae3b26"}]}}}, {"type": "participant", "id": "0825ccc6-a9d5-460b-9339-c4a9bf694ce0", "attributes": {"stats": {"DBNOs": 1, "assists": 0, "boosts": 2, "damageDealt": 157.41998, "deathType": "byplayer", "headshotKills": 0, "heals": 2, "killPlace": 61, "killStreaks": 0, "kills": 0, "longestKill": 0, "name": "Moonlight12-16", "playerId": "account.eeac01ce3adc4df1824db950b51c1e00", "revives": 0, "rideDistance": 0, "roadKills": 0, "swimDistance": 0, "teamKills": 0, "timeSurvived": 365, "vehicleDestroys": 0, "walkDistance": 807.2523, "weaponsAcquired": 6, "winPlace": 12}, "actor": "", "shardId": "steam"}}, {"type": "participant", "id": "4302b91c-ecdd-4cf2-b883-000a77c4d052", "attributes": {"stats": {"DBNOs": 1, "assists": 0, "boosts": 1, "damageDealt": 260.09375, "deathType": "byplayer", "headshotKills": 0, "heals": 2, "killPlace": 44, "killStreaks": 1, "kills": 1, "longestKill": 22.137201, "name": "zZzZClr", "playerId": "account.3af80738651648a1892be763ca1baadd", "revives": 0, "rideDistance": 0, "roadKills": 0, "swimDistance": 0, "teamKills": 0, "timeSurvived": 336, "vehicleDestroys": 0, "walkDistance": 561.3531, "weaponsAcquired": 4, "winPlace": 19}, "actor": "", "shardId": "steam"}}, {"type": "roster", "id": "af05d2d3-1c2d-48ce-b8fc-6eb5f0ddaaf8", "attributes": {"stats": {"rank": 29, "teamId": 13}, "won": "false", "shardId": "steam"}, "relationships": {"team": {"data": null}, "participants": {"data": [{"type": "participant", "id": "d677418d-c86f-43ed-8fe8-08458b0d512a"}, {"type": "participant", "id": "b34d910d-5e42-4279-b893-1375ef51c754"}, {"type": "participant", "id": "c8cb97c2-a0a9-4e96-a1f4-f9e077830ac5"}]}}}, {"type": "participant", "id": "dca472b6-5ea0-417e-aed3-a3b1ea522ec7", "attributes": {"stats": {"DBNOs": 0, "assists": 0, "boosts": 0, "damageDealt": 0, "deathType": "byplayer", "headshotKills": 0, "heals": 0, "killPlace": 97, "killStreaks": 0, "kills": 0, "longestKill": 0, "name": "CXDLOVEQJ12", "playerId": "account.7744def224e648f8b1703633de5011bb", "revives": 0, "rideDistance": 0, "roadKills": 0, "swimDistance": 0, "teamKills": 0, "timeSurvived": 126, "vehicleDestroys": 0, "walkDistance": 90.02622, "weaponsAcquired": 2, "winPlace": 27}, "actor": "", "shardId": "steam"}}, {"type": "participant", "id": "32bcd07e-02b6-4801-8400-2cfb2a130fca", "attributes": {"stats": {"DBNOs": 0, "assists": 1, "boosts": 3, "damageDealt": 106.95, "deathType": "byplayer", "headshotKills": 0, "heals": 3, "killPlace": 59, "killStreaks": 0, "kills": 0, "longestKill": 0, "name": "FaTeAdan", "playerId": "account.556ef9c4ce71402ca8215a9aebd3fa57", "revives": 0, "rideDistance": 1139.4733, "roadKills": 0, "swimDistance": 0, "teamKills": 0, "timeSurvived": 797, "vehicleDestroys": 0, "walkDistance": 1979.1753, "weaponsAcquired": 11, "winPlace": 11}, "actor": "", "shardId": "steam"}}, {"type": "participant", "id": "79c7ad61-30a6-4279-bc94-46056b39eec5", "attributes": {"shardId": "steam", "stats": {"DBNOs": 1, "assists": 1, "boosts": 1, "damageDealt": 220.31206, "deathType": "byplayer", "headshotKills": 1, "heals": 0, "killPlace": 39, "killStreaks": 1, "kills": 1, "longestKill": 7.2556562, "name": "Lcjzsvkx860", "playerId": "account.67ec0498a67242be977f706e92525f8d", "revives": 1, "rideDistance": 5945.072, "roadKills": 0, "swimDistance": 0, "teamKills": 0, "timeSurvived": 857, "vehicleDestroys": 0, "walkDistance": 1568.9407, "weaponsAcquired": 11, "winPlace": 11}, "actor": ""}}, {"type": "participant", "id": "d2b6f019-1266-4913-a7f9-bfcca95b500f", "attributes": {"stats": {"DBNOs": 2, "assists": 0, "boosts": 2, "damageDealt": 237.03168, "deathType": "byzone", "headshotKills": 0, "heals": 5, "killPlace": 10, "killStreaks": 1, "kills": 3, "longestKill": 86.57213, "name": "sodagreen_13", "playerId": "account.b9dc9b47f3d9455eb44c81f95acdd327", "revives": 2, "rideDistance": 1788.6973, "roadKills": 0, "swimDistance": 0, "teamKills": 0, "timeSurvived": 891, "vehicleDestroys": 0, "walkDistance": 1663.2554, "weaponsAcquired": 14, "winPlace": 2}, "actor": "", "shardId": "steam"}}, {"type": "participant", "id": "287864c8-eeb8-492f-af75-099812958c92", "attributes": {"stats": {"DBNOs": 2, "assists": 0, "boosts": 3, "damageDealt": 65.12746, "deathType": "byplayer", "headshotKills": 0, "heals": 1, "killPlace": 65, "killStreaks": 0, "kills": 0, "longestKill": 0, "name": "HuaiSHanK", "playerId": "account.90e168ca6cf44c60b11fd6b8f86da626", "revives": 0, "rideDistance": 1852.0865, "roadKills": 0, "swimDistance": 0, "teamKills": 0, "timeSurvived": 489, "vehicleDestroys": 0, "walkDistance": 938.8202, "weaponsAcquired": 3, "winPlace": 14}, "actor": "", "shardId": "steam"}}, {"type": "participant", "id": "6197436c-5ac9-4edf-b6ae-91459b19ae7e", "attributes": {"stats": {"DBNOs": 0, "assists": 0, "boosts": 0, "damageDealt": 7.936313, "deathType": "byplayer", "headshotKills": 0, "heals": 0, "killPlace": 87, "killStreaks": 0, "kills": 0, "longestKill": 0, "name": "b1eganmao_-", "playerId": "account.7d73bf7cef874ce28f3be5607d99e2ed", "revives": 0, "rideDistance": 0, "roadKills": 0, "swimDistance": 0, "teamKills": 0, "timeSurvived": 155, "vehicleDestroys": 0, "walkDistance": 58.661564, "weaponsAcquired": 1, "winPlace": 23}, "actor": "", "shardId": "steam"}}, {"type": "participant", "id": "faf41400-103c-4c3f-9073-b6e19ad400d8", "attributes": {"stats": {"DBNOs": 0, "assists": 0, "boosts": 0, "damageDealt": 0, "deathType": "byplayer", "headshotKills": 0, "heals": 0, "killPlace": 64, "killStreaks": 0, "kills": 0, "longestKill": 0, "name": "inxxi-_", "playerId": "account.a5ddd4b04c0444c0aa616fc5ca03d93b", "revives": 0, "rideDistance": 0, "roadKills": 0, "swimDistance": 0, "teamKills": 0, "timeSurvived": 151, "vehicleDestroys": 0, "walkDistance": 208.19635, "weaponsAcquired": 3, "winPlace": 13}, "actor": "", "shardId": "steam"}}, {"type": "roster", "id": "90c55ca3-de28-4b40-b3e9-bc4020131b29", "attributes": {"stats": {"rank": 7, "teamId": 9}, "won": "false", "shardId": "steam"}, "relationships": {"participants": {"data": [{"type": "participant", "id": "c8e19613-2000-41d3-8091-937fef46a8ac"}, {"type": "participant", "id": "4dd0f11c-5291-4331-a019-4fa98caa08fc"}, {"type": "participant", "id": "f8a1bc82-b0bc-445a-8407-ed23009f9773"}, {"type": "participant", "id": "2a992e7b-1757-43bb-84ef-cdb88a242e8d"}]}, "team": {"data": null}}}, {"type": "roster", "id": "7db93a5b-d120-43a4-8428-49f15d2b2fd6", "attributes": {"stats": {"rank": 28, "teamId": 2}, "won": "false", "shardId": "steam"}, "relationships": {"team": {"data": null}, "participants": {"data": [{"type": "participant", "id": "44f4d062-8ace-4819-a4ab-ee8542829a1c"}, {"type": "participant", "id": "e2b323da-3463-4ed2-8540-59c976ebae68"}]}}}, {"type": "roster", "id": "f82defa0-8783-4ac4-9f3d-7b4ba594aca8", "attributes": {"shardId": "steam", "stats": {"rank": 27, "teamId": 14}, "won": "false"}, "relationships": {"team": {"data": null}, "participants": {"data": [{"type": "participant", "id": "9793c772-0a1d-429c-9621-78386ca2a972"}, {"type": "participant", "id": "90bc8203-dced-40bc-8cb1-769c93d7cfae"}, {"type": "participant", "id": "6ca058b3-aa3c-4647-a89a-aeafae6e7e62"}, {"type": "participant", "id": "b59bf495-9352-46a3-a12f-914eb9869715"}]}}}, {"type": "roster", "id": "af08ca1d-0a19-4841-9772-9028a1726777", "attributes": {"stats": {"rank": 20, "teamId": 20}, "won": "false", "shardId": "steam"}, "relationships": {"team": {"data": null}, "participants": {"data": [{"type": "participant", "id": "cafb2c70-ddbb-44ce-b1b3-8b6f19d74cf0"}, {"type": "participant", "id": "0a2f20f8-640f-4da2-9074-5b78c3b42f5f"}, {"type": "participant", "id": "32089926-0ce4-44da-8283-34e3140e5013"}]}}}, {"type": "participant", "id": "4540d508-f6a2-4e17-902c-95392bd2a52e", "attributes": {"actor": "", "shardId": "steam", "stats": {"DBNOs": 0, "assists": 0, "boosts": 1, "damageDealt": 0, "deathType": "byplayer", "headshotKills": 0, "heals": 0, "killPlace": 70, "killStreaks": 0, "kills": 0, "longestKill": 0, "name": "xiaomengmei123", "playerId": "account.014aa66278aa48808435eb6a3ff8f902", "revives": 0, "rideDistance": 0, "roadKills": 0, "swimDistance": 0, "teamKills": 0, "timeSurvived": 255, "vehicleDestroys": 0, "walkDistance": 581.22125, "weaponsAcquired": 7, "winPlace": 16}}}, {"type": "participant", "id": "c11fe62e-11f2-4456-8a55-22b235f99549", "attributes": {"stats": {"DBNOs": 2, "assists": 0, "boosts": 4, "damageDealt": 250.34383, "deathType": "byplayer", "headshotKills": 1, "heals": 1, "killPlace": 22, "killStreaks": 2, "kills": 2, "longestKill": 26.41679, "name": "Aeloutv", "playerId": "account.e072764666f84b1ba68b7016b1b7ddd8", "revives": 0, "rideDistance": 5336.3584, "roadKills": 0, "swimDistance": 0, "teamKills": 0, "timeSurvived": 837, "vehicleDestroys": 0, "walkDistance": 1181.3214, "weaponsAcquired": 10, "winPlace": 10}, "actor": "", "shardId": "steam"}}, {"type": "participant", "id": "aba6b2a8-0f18-48e9-9818-f01d3348e42e", "attributes": {"stats": {"DBNOs": 0, "assists": 0, "boosts": 0, "damageDealt": 0, "deathType": "byplayer", "headshotKills": 0, "heals": 0, "killPlace": 79, "killStreaks": 0, "kills": 0, "longestKill": 0, "name": "woaishine33", "playerId": "account.f2b48e7870e5425e8499dd9bc2559990", "revives": 0, "rideDistance": 0, "roadKills": 0, "swimDistance": 0, "teamKills": 0, "timeSurvived": 261, "vehicleDestroys": 0, "walkDistance": 302.13962, "weaponsAcquired": 4, "winPlace": 21}, "actor": "", "shardId": "steam"}}, {"type": "participant", "id": "c2cf7a32-2942-46cc-ac1a-c47689661f25", "attributes": {"stats": {"DBNOs": 4, "assists": 3, "boosts": 9, "damageDealt": 386.40784, "deathType": "byplayer", "headshotKills": 0, "heals": 12, "killPlace": 17, "killStreaks": 1, "kills": 2, "longestKill": 74.03606, "name": "Best-VI", "playerId": "account.1fd02e3bf1124f71875827c9b25b4164", "revives": 1, "rideDistance": 7527.3955, "roadKills": 0, "swimDistance": 0, "teamKills": 0, "timeSurvived": 1182, "vehicleDestroys": 0, "walkDistance": 2409.6655, "weaponsAcquired": 16, "winPlace": 4}, "actor": "", "shardId": "steam"}}, {"type": "participant", "id": "fbc53ad0-55a2-4d67-bcb6-c039cc868d58", "attributes": {"stats": {"DBNOs": 1, "assists": 0, "boosts": 1, "damageDealt": 163.47638, "deathType": "byplayer", "headshotKills": 0, "heals": 2, "killPlace": 43, "killStreaks": 1, "kills": 1, "longestKill": 35.326107, "name": "Endless-Mist", "playerId": "account.7968fdec12794b2d9ef92a49601161fb", "revives": 0, "rideDistance": 0, "roadKills": 0, "swimDistance": 0, "teamKills": 0, "timeSurvived": 338, "vehicleDestroys": 0, "walkDistance": 658.7655, "weaponsAcquired": 3, "winPlace": 19}, "actor": "", "shardId": "steam"}}, {"type": "participant", "id": "0711d883-3093-4c41-bbd8-f7521ca78844", "attributes": {"stats": {"DBNOs": 0, "assists": 0, "boosts": 2, "damageDealt": 82.89998, "deathType": "byplayer", "headshotKills": 0, "heals": 0, "killPlace": 77, "killStreaks": 0, "kills": 0, "longestKill": 0, "name": "Saozi__Kaimen", "playerId": "account.6fdcf4d41af345c0a496a9ca7c46ef30", "revives": 0, "rideDistance": 0, "roadKills": 0, "swimDistance": 0, "teamKills": 0, "timeSurvived": 261, "vehicleDestroys": 0, "walkDistance": 520.9126, "weaponsAcquired": 3, "winPlace": 21}, "actor": "", "shardId": "steam"}}, {"type": "participant", "id": "160e6a56-09a6-4351-a9c5-aa3e1ea2c8d2", "attributes": {"stats": {"DBNOs": 1, "assists": 0, "boosts": 0, "damageDealt": 100.00001, "deathType": "byplayer", "headshotKills": 0, "heals": 0, "killPlace": 86, "killStreaks": 0, "kills": 0, "longestKill": 0, "name": "1iteey", "playerId": "account.b4a3b26a6c664c168c80f82e9d325985", "revives": 0, "rideDistance": 0, "roadKills": 0, "swimDistance": 0, "teamKills": 0, "timeSurvived": 173, "vehicleDestroys": 0, "walkDistance": 153.76335, "weaponsAcquired": 1, "winPlace": 23}, "actor": "", "shardId": "steam"}}, {"type": "roster", "id": "0ec3ade7-6970-40b9-9cc5-c21d8be538b3", "attributes": {"shardId": "steam", "stats": {"rank": 16, "teamId": 22}, "won": "false"}, "relationships": {"participants": {"data": [{"type": "participant", "id": "58a604ec-55f2-4f16-a7e1-534d2a3c6a6f"}, {"type": "participant", "id": "4540d508-f6a2-4e17-902c-95392bd2a52e"}, {"type": "participant", "id": "e5c92531-bf7d-49e3-af89-bc744e054ed5"}, {"type": "participant", "id": "e762af82-c6cc-42e9-bd6d-881f8475cd08"}]}, "team": {"data": null}}}], "links": {"self": "https://api-origin.pubg-odapi.pubg.io/shards/steam/matches/e329e248-d2e1-4575-8e01-7622ee0b0a60"}, "meta": {}}